{
  "updatedAt": "2026-07-13T14:17:04.030Z",
  "market": {
    "symbol": "QQQ",
    "price": 714.83,
    "prevClose": 725.51,
    "change": -10.67999999999995,
    "changePct": -1.4720679246323207,
    "high": 718.78,
    "low": 712.535
  },
  "prices": {
    "TSM": {
      "price": 428.6,
      "prevClose": 434.11,
      "high": 437.745,
      "low": 425.68,
      "timestamp": "2026-07-13T10:17:00.572194726-04:00"
    },
    "QQQ": {
      "price": 714.83,
      "prevClose": 725.51,
      "high": 718.78,
      "low": 712.535,
      "timestamp": "2026-07-13T10:17:02.762381538-04:00"
    },
    "AMD": {
      "price": 538.9,
      "prevClose": 557.89,
      "high": 545.17,
      "low": 527.135,
      "timestamp": "2026-07-13T10:17:02.624619678-04:00"
    }
  },
  "metals": {
    "gold": 4050.315,
    "silver": 58.318,
    "updated": "2026-07-13T13:59:12.947Z"
  }
}