{
  "updatedAt": "2026-07-08T14:50:34.487Z",
  "market": {
    "symbol": "QQQ",
    "price": 704.125,
    "prevClose": 709.43,
    "change": -5.30499999999995,
    "changePct": -0.7477834317691598,
    "high": 709.925,
    "low": 702.68
  },
  "prices": {
    "QQQ": {
      "price": 704.125,
      "prevClose": 709.43,
      "high": 709.925,
      "low": 702.68,
      "timestamp": "2026-07-08T10:50:33.807824041-04:00"
    },
    "TSM": {
      "price": 431.88,
      "prevClose": 432.57,
      "high": 440.3,
      "low": 428.87,
      "timestamp": "2026-07-08T10:50:32.739332904-04:00"
    },
    "AMD": {
      "price": 507.52,
      "prevClose": 516.11,
      "high": 522.72,
      "low": 503.91,
      "timestamp": "2026-07-08T10:50:34.015236947-04:00"
    }
  },
  "metals": {
    "gold": 4071.22,
    "silver": 58.467,
    "updated": "2026-07-08T13:58:26.384Z"
  }
}