{
  "updatedAt": "2026-07-06T16:50:28.492Z",
  "market": {
    "symbol": "QQQ",
    "price": 724.64,
    "prevClose": 712.6,
    "change": 12.039999999999964,
    "changePct": 1.6895874263261244,
    "high": 726.19,
    "low": 718.53
  },
  "prices": {
    "QQQ": {
      "price": 724.64,
      "prevClose": 712.6,
      "high": 726.19,
      "low": 718.53,
      "timestamp": "2026-07-06T12:50:27.814614990-04:00"
    },
    "TSM": {
      "price": 455.87,
      "prevClose": 434.16,
      "high": 460.075,
      "low": 445.23,
      "timestamp": "2026-07-06T12:50:27.327223597-04:00"
    },
    "AMD": {
      "price": 559.02,
      "prevClose": 517.82,
      "high": 572.5,
      "low": 527.5,
      "timestamp": "2026-07-06T12:50:26.224199595-04:00"
    }
  },
  "metals": {
    "gold": 4148.425,
    "silver": 61.778,
    "updated": "2026-07-06T16:00:04.837Z"
  }
}