{
  "updatedAt": "2026-07-21T16:20:17.048Z",
  "market": {
    "symbol": "QQQ",
    "price": 708.9,
    "prevClose": 696.06,
    "change": 12.840000000000032,
    "changePct": 1.8446685630549138,
    "high": 709.145,
    "low": 702.665
  },
  "prices": {
    "QQQ": {
      "price": 708.9,
      "prevClose": 696.06,
      "high": 709.145,
      "low": 702.665,
      "timestamp": "2026-07-21T12:20:16.441286388-04:00"
    },
    "TSM": {
      "price": 421.825,
      "prevClose": 402.3,
      "high": 422.265,
      "low": 413.65,
      "timestamp": "2026-07-21T12:20:14.635925937-04:00"
    },
    "AMD": {
      "price": 536.43,
      "prevClose": 503.57,
      "high": 536.71,
      "low": 522.08,
      "timestamp": "2026-07-21T12:20:15.927745082-04:00"
    }
  },
  "metals": {
    "gold": null,
    "silver": null,
    "updated": null
  }
}