{
  "updatedAt": "2026-07-24T15:40:15.123Z",
  "market": {
    "symbol": "QQQ",
    "price": 691.095,
    "prevClose": 691.96,
    "change": -0.8650000000000091,
    "changePct": -0.12500722585120658,
    "high": 693.9,
    "low": 683.44
  },
  "prices": {
    "AMD": {
      "price": 533.835,
      "prevClose": 539.69,
      "high": 548.725,
      "low": 518.33,
      "timestamp": "2026-07-24T11:40:12.279468291-04:00"
    },
    "QQQ": {
      "price": 691.095,
      "prevClose": 691.96,
      "high": 693.9,
      "low": 683.44,
      "timestamp": "2026-07-24T11:40:14.072404745-04:00"
    },
    "TSM": {
      "price": 407.445,
      "prevClose": 415.58,
      "high": 415.38,
      "low": 402.79,
      "timestamp": "2026-07-24T11:40:02.465101211-04:00"
    }
  },
  "metals": {
    "gold": null,
    "silver": null,
    "updated": null
  }
}