{
  "updatedAt": "2026-06-29T16:10:16.568Z",
  "market": {
    "symbol": "QQQ",
    "price": 719.585,
    "prevClose": 706.52,
    "change": 13.065000000000055,
    "changePct": 1.8492045518881357,
    "high": 719.975,
    "low": 705.06
  },
  "prices": {
    "QQQ": {
      "price": 719.585,
      "prevClose": 706.52,
      "high": 719.975,
      "low": 705.06,
      "timestamp": "2026-06-29T12:10:15.857822018-04:00"
    },
    "TSM": {
      "price": 449.36,
      "prevClose": 432.35,
      "high": 450.04,
      "low": 431.065,
      "timestamp": "2026-06-29T12:10:13.788442300-04:00"
    },
    "AMD": {
      "price": 527.44,
      "prevClose": 521.58,
      "high": 535.085,
      "low": 495.58,
      "timestamp": "2026-06-29T12:10:15.706144005-04:00"
    }
  },
  "metals": {
    "gold": 4027.34,
    "silver": 58.114,
    "updated": "2026-06-29T15:59:20.270Z"
  }
}