{
  "updatedAt": "2026-06-25T14:45:20.369Z",
  "market": {
    "symbol": "QQQ",
    "price": 712.605,
    "prevClose": 710.62,
    "change": 1.9850000000000136,
    "changePct": 0.2793335397258751,
    "high": 727.58,
    "low": 705.195
  },
  "prices": {
    "QQQ": {
      "price": 712.605,
      "prevClose": 710.62,
      "high": 727.58,
      "low": 705.195,
      "timestamp": "2026-06-25T10:45:19.664134164-04:00"
    },
    "TSM": {
      "price": 439.865,
      "prevClose": 440.83,
      "high": 456.8,
      "low": 433.45,
      "timestamp": "2026-06-25T10:44:59.994915882-04:00"
    },
    "AMD": {
      "price": 517.28,
      "prevClose": 519.74,
      "high": 550.74,
      "low": 507.15,
      "timestamp": "2026-06-25T10:45:18.030598047-04:00"
    }
  },
  "metals": {
    "gold": 4005.25,
    "silver": 57.0915,
    "updated": "2026-06-25T14:00:05.736Z"
  }
}