{
  "updatedAt": "2026-07-15T14:15:15.935Z",
  "market": {
    "symbol": "QQQ",
    "price": 720.515,
    "prevClose": 719.69,
    "change": 0.8249999999999318,
    "changePct": 0.11463268907445313,
    "high": 724.755,
    "low": 718.765
  },
  "prices": {
    "QQQ": {
      "price": 720.515,
      "prevClose": 719.69,
      "high": 724.755,
      "low": 718.765,
      "timestamp": "2026-07-15T10:15:14.880992688-04:00"
    },
    "TSM": {
      "price": 422.27,
      "prevClose": 420.39,
      "high": 428.72,
      "low": 421.095,
      "timestamp": "2026-07-15T10:15:10.069435460-04:00"
    },
    "AMD": {
      "price": 542.005,
      "prevClose": 548.13,
      "high": 559,
      "low": 541.33,
      "timestamp": "2026-07-15T10:15:14.315891186-04:00"
    }
  },
  "metals": {
    "gold": 4063.06,
    "silver": 58.365,
    "updated": "2026-07-15T13:59:13.339Z"
  }
}