{
  "updatedAt": "2026-07-07T18:40:34.276Z",
  "market": {
    "symbol": "QQQ",
    "price": 711.655,
    "prevClose": 722.82,
    "change": -11.165000000000077,
    "changePct": -1.5446445864807388,
    "high": 716.515,
    "low": 704.715
  },
  "prices": {
    "TSM": {
      "price": 433.35,
      "prevClose": 451.79,
      "high": 444.33,
      "low": 428.11,
      "timestamp": "2026-07-07T14:40:30.250913594-04:00"
    },
    "QQQ": {
      "price": 711.655,
      "prevClose": 722.82,
      "high": 716.515,
      "low": 704.715,
      "timestamp": "2026-07-07T14:40:33.508648588-04:00"
    },
    "AMD": {
      "price": 520.85,
      "prevClose": 552.05,
      "high": 532.87,
      "low": 503.165,
      "timestamp": "2026-07-07T14:40:32.941885242-04:00"
    }
  },
  "metals": {
    "gold": 4145.235,
    "silver": 61.022,
    "updated": "2026-07-07T18:00:26.109Z"
  }
}