{
  "updatedAt": "2026-07-15T13:10:30.410Z",
  "market": {
    "symbol": "QQQ",
    "price": 724.64,
    "prevClose": 719.69,
    "change": 4.949999999999932,
    "changePct": 0.6877961344467662,
    "high": 724.755,
    "low": 721.89
  },
  "prices": {
    "QQQ": {
      "price": 724.64,
      "prevClose": 719.69,
      "high": 724.755,
      "low": 721.89,
      "timestamp": "2026-07-15T09:06:45.084632981-04:00"
    },
    "TSM": {
      "price": 426.1,
      "prevClose": 420.39,
      "high": 426.54,
      "low": 424.87,
      "timestamp": "2026-07-15T09:05:20.025144277-04:00"
    },
    "AMD": {
      "price": 558,
      "prevClose": 548.13,
      "high": 558.96,
      "low": 553.8,
      "timestamp": "2026-07-15T09:03:33.735286259-04:00"
    }
  },
  "metals": {
    "gold": 4070.49,
    "silver": 58.721,
    "updated": "2026-07-15T12:59:06.003Z"
  }
}