{
  "updatedAt": "2026-06-23T16:11:58.371Z",
  "market": {
    "symbol": "QQQ",
    "price": 720.06,
    "prevClose": 737.95,
    "change": -17.8900000000001,
    "changePct": -2.4242834880412083,
    "high": 723.68,
    "low": 713.24
  },
  "prices": {
    "QQQ": {
      "price": 720.06,
      "prevClose": 737.95,
      "high": 723.68,
      "low": 713.24,
      "timestamp": "2026-06-23T12:11:57.899233680-04:00"
    },
    "AMD": {
      "price": 527.54,
      "prevClose": 551.63,
      "high": 527.805,
      "low": 506.88,
      "timestamp": "2026-06-23T12:11:56.351521868-04:00"
    }
  },
  "metals": {
    "gold": 4136.23,
    "silver": 62.2715,
    "updated": "2026-06-23T16:11:23.858Z"
  }
}