{
  "updatedAt": "2026-06-30T14:40:19.476Z",
  "market": {
    "symbol": "QQQ",
    "price": 733.1,
    "prevClose": 724.08,
    "change": 9.019999999999982,
    "changePct": 1.2457187051154541,
    "high": 733.875,
    "low": 723.22
  },
  "prices": {
    "QQQ": {
      "price": 733.1,
      "prevClose": 724.08,
      "high": 733.875,
      "low": 723.22,
      "timestamp": "2026-06-30T10:40:18.984802442-04:00"
    },
    "TSM": {
      "price": 467.2,
      "prevClose": 455.1,
      "high": 471.3,
      "low": 452.1,
      "timestamp": "2026-06-30T10:40:17.107580070-04:00"
    },
    "AMD": {
      "price": 557.64,
      "prevClose": 539.49,
      "high": 564.775,
      "low": 539.28,
      "timestamp": "2026-06-30T10:40:18.200640342-04:00"
    }
  },
  "metals": {
    "gold": 4029.15,
    "silver": 59.237,
    "updated": "2026-06-30T13:59:24.854Z"
  }
}