{
  "updatedAt": "2026-07-21T17:20:16.611Z",
  "market": {
    "symbol": "QQQ",
    "price": 709.29,
    "prevClose": 696.06,
    "change": 13.230000000000018,
    "changePct": 1.9006982156710657,
    "high": 709.95,
    "low": 702.665
  },
  "prices": {
    "TSM": {
      "price": 423.9,
      "prevClose": 402.3,
      "high": 424.315,
      "low": 413.65,
      "timestamp": "2026-07-21T13:20:15.610668188-04:00"
    },
    "QQQ": {
      "price": 709.29,
      "prevClose": 696.06,
      "high": 709.95,
      "low": 702.665,
      "timestamp": "2026-07-21T13:20:15.935241845-04:00"
    },
    "AMD": {
      "price": 541.58,
      "prevClose": 503.57,
      "high": 544.01,
      "low": 522.08,
      "timestamp": "2026-07-21T13:20:12.777289950-04:00"
    }
  },
  "metals": {
    "gold": null,
    "silver": null,
    "updated": null
  }
}