{
  "updatedAt": "2026-07-02T17:35:14.679Z",
  "market": {
    "symbol": "QQQ",
    "price": 710.105,
    "prevClose": 725.17,
    "change": -15.06499999999994,
    "changePct": -2.0774439097039235,
    "high": 731.23,
    "low": 708.875
  },
  "prices": {
    "QQQ": {
      "price": 710.105,
      "prevClose": 725.17,
      "high": 731.23,
      "low": 708.875,
      "timestamp": "2026-07-02T13:35:13.857739870-04:00"
    },
    "TSM": {
      "price": 432.31,
      "prevClose": 444.23,
      "high": 461.41,
      "low": 430.905,
      "timestamp": "2026-07-02T13:35:13.733169452-04:00"
    },
    "AMD": {
      "price": 512.99,
      "prevClose": 540.88,
      "high": 552.58,
      "low": 509.84,
      "timestamp": "2026-07-02T13:35:13.088650303-04:00"
    }
  },
  "metals": {
    "gold": 4117.85,
    "silver": 60.812,
    "updated": "2026-07-02T16:59:11.318Z"
  }
}