{
  "updatedAt": "2026-07-07T19:40:35.011Z",
  "market": {
    "symbol": "QQQ",
    "price": 707.535,
    "prevClose": 722.82,
    "change": -15.285000000000082,
    "changePct": -2.114634348800543,
    "high": 716.515,
    "low": 704.715
  },
  "prices": {
    "QQQ": {
      "price": 707.535,
      "prevClose": 722.82,
      "high": 716.515,
      "low": 704.715,
      "timestamp": "2026-07-07T15:40:34.690907424-04:00"
    },
    "TSM": {
      "price": 430.58,
      "prevClose": 451.79,
      "high": 444.33,
      "low": 428.11,
      "timestamp": "2026-07-07T15:40:34.527692194-04:00"
    },
    "AMD": {
      "price": 508.97,
      "prevClose": 552.05,
      "high": 532.87,
      "low": 503.165,
      "timestamp": "2026-07-07T15:40:34.584444593-04:00"
    }
  },
  "metals": {
    "gold": 4124.86,
    "silver": 60.403,
    "updated": "2026-07-07T19:00:27.908Z"
  }
}