{
  "updatedAt": "2026-07-15T14:00:36.090Z",
  "market": {
    "symbol": "QQQ",
    "price": 721.185,
    "prevClose": 719.69,
    "change": 1.4949999999998909,
    "changePct": 0.20772832747431408,
    "high": 724.755,
    "low": 718.765
  },
  "prices": {
    "QQQ": {
      "price": 721.185,
      "prevClose": 719.69,
      "high": 724.755,
      "low": 718.765,
      "timestamp": "2026-07-15T10:00:35.068059572-04:00"
    },
    "TSM": {
      "price": 423.55,
      "prevClose": 420.39,
      "high": 428.72,
      "low": 421.095,
      "timestamp": "2026-07-15T10:00:33.979676608-04:00"
    },
    "AMD": {
      "price": 545.13,
      "prevClose": 548.13,
      "high": 559,
      "low": 542.705,
      "timestamp": "2026-07-15T10:00:34.630850817-04:00"
    }
  },
  "metals": {
    "gold": 4063.06,
    "silver": 58.365,
    "updated": "2026-07-15T13:59:13.339Z"
  }
}